[
      {
            "Rankas": "1",
            "Nuotrauka": "https://lkl.lt/media/players/890x520/d4f9e15e5b9d29279b5ebcb00293fc85.png",
            "Zaidejas": "Ivan Buva",
            "Klubas": "Rytas",
            "Rungtynes": "24",
            "Suma": "485",
            "Vidurkis": "20.21"
      },
      {
            "Rankas": "2",
            "Nuotrauka": "https://lkl.lt/media/players/890x520/6946db6030a5b66b9db25ccf4104c5d7.png",
            "Zaidejas": "Patrick Miller",
            "Klubas": "Uniclub Casino - Juventus",
            "Rungtynes": "26",
            "Suma": "476",
            "Vidurkis": "18.31"
      },
      {
            "Rankas": "3",
            "Nuotrauka": "https://lkl.lt/media/players/890x520/9461867c1adecaa0c61d2ab2b0c48c8d.png",
            "Zaidejas": "Amar Sylla",
            "Klubas": "Nevėžis–Optibet",
            "Rungtynes": "29",
            "Suma": "498",
            "Vidurkis": "17.17"
      },
      {
            "Rankas": "4",
            "Nuotrauka": "https://lkl.lt/media/players/890x520/f0ecbfbdd0f8d71bc678b3a5e5a72322.png",
            "Zaidejas": "Juan Palacios",
            "Klubas": "CBet",
            "Rungtynes": "20",
            "Suma": "339",
            "Vidurkis": "16.95"
      },
      {
            "Rankas": "5",
            "Nuotrauka": "https://lkl.lt/media/players/890x520/d14279da2dd70b91551a55b80048725e.png",
            "Zaidejas": "Jonathan Elmore",
            "Klubas": "Šiauliai-7bet",
            "Rungtynes": "25",
            "Suma": "421",
            "Vidurkis": "16.84"
      },
      {
            "Rankas": "6",
            "Nuotrauka": "https://lkl.lt/media/players/890x520/eb09805b2ba4b9f9ee69fdaf8c6ab1c0.png",
            "Zaidejas": "Emmanuel Lecomte",
            "Klubas": "CBet",
            "Rungtynes": "23",
            "Suma": "382",
            "Vidurkis": "16.61"
      },
      {
            "Rankas": "7",
            "Nuotrauka": "https://lkl.lt/media/players/890x520/4de3cbceb5de01381f663ef20601d16d.png",
            "Zaidejas": "Giedrius Staniulis",
            "Klubas": "Šiauliai-7bet",
            "Rungtynes": "27",
            "Suma": "445",
            "Vidurkis": "16.48"
      },
      {
            "Rankas": "8",
            "Nuotrauka": "https://lkl.lt/media/players/890x520/d1dfa9b325dafe7fdcaf090d02273c4c.png",
            "Zaidejas": "Deividas Gailius",
            "Klubas": "Neptūnas",
            "Rungtynes": "26",
            "Suma": "428",
            "Vidurkis": "16.46"
      },
      {
            "Rankas": "9",
            "Nuotrauka": "https://lkl.lt/media/players/890x520/88bda3c3d2366db6d663881a3fcdabdd.png",
            "Zaidejas": "Edgaras Ulanovas",
            "Klubas": "Žalgiris",
            "Rungtynes": "26",
            "Suma": "413",
            "Vidurkis": "15.88"
      },
      {
            "Rankas": "10",
            "Nuotrauka": "https://lkl.lt/media/players/890x520/b7112e549e80247cbdbf1d57419b310c.png",
            "Zaidejas": "Dorde Gagič",
            "Klubas": "Lietkabelis",
            "Rungtynes": "30",
            "Suma": "444",
            "Vidurkis": "14.80"
      },
      {
            "Rankas": "11",
            "Nuotrauka": "https://lkl.lt/media/players/890x520/521e14224bbad7de19a3e470023734ce.png",
            "Zaidejas": "Benas Griciūnas",
            "Klubas": "Neptūnas",
            "Rungtynes": "29",
            "Suma": "420",
            "Vidurkis": "14.48"
      },
      {
            "Rankas": "12",
            "Nuotrauka": "https://lkl.lt/media/players/890x520/03470cd95f2896622729612a2947fe01.png",
            "Zaidejas": "Rokas Gustys",
            "Klubas": "Uniclub Casino - Juventus",
            "Rungtynes": "29",
            "Suma": "416",
            "Vidurkis": "14.34"
      },
      {
            "Rankas": "13",
            "Nuotrauka": "https://lkl.lt/media/players/890x520/8eaa1a6be3284fc63b4c46e6d2f1ccc2.png",
            "Zaidejas": "Tyler Cavanaugh",
            "Klubas": "Žalgiris",
            "Rungtynes": "25",
            "Suma": "346",
            "Vidurkis": "13.84"
      },
      {
            "Rankas": "14",
            "Nuotrauka": "https://lkl.lt/media/players/890x520/bc7f07dc80a18edecd311e0c734866a9.png",
            "Zaidejas": "Gytis Radzevičius",
            "Klubas": "Rytas",
            "Rungtynes": "29",
            "Suma": "401",
            "Vidurkis": "13.83"
      },
      {
            "Rankas": "15",
            "Nuotrauka": "https://lkl.lt/media/players/890x520/68f62343148b3bb8c27d1bdeafbf52e6.png",
            "Zaidejas": "Markell Johnson",
            "Klubas": "Pieno žvaigždės",
            "Rungtynes": "23",
            "Suma": "317",
            "Vidurkis": "13.78"
      },
      {
            "Rankas": "16",
            "Nuotrauka": "https://lkl.lt/media/players/890x520/860fa6cfc86cfc6e96af75645fdc60ce.png",
            "Zaidejas": "Juwan Josiah Durham",
            "Klubas": "Labas Gas",
            "Rungtynes": "24",
            "Suma": "329",
            "Vidurkis": "13.71"
      },
      {
            "Rankas": "17",
            "Nuotrauka": "https://lkl.lt/media/players/890x520/b05032a3d55b7b321e50a248c01d24b8.png",
            "Zaidejas": "Žygimantas Janavičius",
            "Klubas": "Neptūnas",
            "Rungtynes": "29",
            "Suma": "393",
            "Vidurkis": "13.55"
      },
      {
            "Rankas": "18",
            "Nuotrauka": "https://lkl.lt/media/players/890x520/59c0ba4e28d959117e002c45a34bb6f9.png",
            "Zaidejas": "Lukas Lekavičius",
            "Klubas": "Žalgiris",
            "Rungtynes": "24",
            "Suma": "325",
            "Vidurkis": "13.54"
      },
      {
            "Rankas": "19",
            "Nuotrauka": "https://lkl.lt/media/players/890x520/c4183950d141903dabf8b567e8048468.png",
            "Zaidejas": "Arnas Butkevičius",
            "Klubas": "Rytas",
            "Rungtynes": "28",
            "Suma": "373",
            "Vidurkis": "13.32"
      },
      {
            "Rankas": "20",
            "Nuotrauka": "https://lkl.lt/media/players/890x520/8d4cfab3bc287b623b522fb2ab9a62c2.png",
            "Zaidejas": "Vytenis Lipkevičius",
            "Klubas": "Lietkabelis",
            "Rungtynes": "25",
            "Suma": "333",
            "Vidurkis": "13.32"
      }
]